teetime/__init__.py
teetime/py.typed
teetime-0.0.3.dist-info/LICENSE
teetime-0.0.3.dist-info/METADATA
teetime-0.0.3.dist-info/WHEEL
teetime-0.0.3.dist-info/top_level.txt
teetime-0.0.3.dist-info/RECORD
