Metadata-Version: 2.1
Name: teetime
Version: 0.0.3
Summary: Add tee like functionally to Popen
Home-page: https://peilonrayz.github.io/teetime
Author: Peilonrayz
Author-email: peilonrayz@gmail.com
License: MIT
Project-URL: Bug Tracker, https://github.com/Peilonrayz/teetime/issues
Project-URL: Documentation, https://peilonrayz.github.io/teetime
Project-URL: Source Code, https://github.com/Peilonrayz/teetime
Keywords: tee popen command
Platform: UNKNOWN
Classifier: Development Status :: 3 - Alpha
Classifier: Environment :: Console
Classifier: Intended Audience :: Developers
Classifier: License :: OSI Approved :: MIT License
Classifier: Operating System :: OS Independent
Classifier: Programming Language :: Python :: 2.7
Classifier: Programming Language :: Python :: 3.4
Classifier: Programming Language :: Python :: 3.5
Classifier: Programming Language :: Python :: 3.6
Classifier: Programming Language :: Python :: 3.7
Classifier: Programming Language :: Python :: 3.8
